GPUmodules/GPUgui.py
GPUmodules/GPUmodule.py
GPUmodules/__init__.py
GPUmodules/env.py
ricks_amdgpu_utils-3.3.14.data/data/share/man/man1/amdgpu-chk.1
ricks_amdgpu_utils-3.3.14.data/data/share/man/man1/amdgpu-ls.1
ricks_amdgpu_utils-3.3.14.data/data/share/man/man1/amdgpu-monitor.1
ricks_amdgpu_utils-3.3.14.data/data/share/man/man1/amdgpu-pac.1
ricks_amdgpu_utils-3.3.14.data/data/share/man/man1/amdgpu-plot.1
ricks_amdgpu_utils-3.3.14.data/data/share/ricks-amdgpu-utils/doc/LICENSE
ricks_amdgpu_utils-3.3.14.data/data/share/ricks-amdgpu-utils/doc/README.md
ricks_amdgpu_utils-3.3.14.data/data/share/ricks-amdgpu-utils/icons/amdgpu-monitor.icon.png
ricks_amdgpu_utils-3.3.14.data/data/share/ricks-amdgpu-utils/icons/amdgpu-pac.icon.png
ricks_amdgpu_utils-3.3.14.data/data/share/ricks-amdgpu-utils/icons/amdgpu-plot.icon.png
ricks_amdgpu_utils-3.3.14.data/scripts/amdgpu-chk
ricks_amdgpu_utils-3.3.14.data/scripts/amdgpu-ls
ricks_amdgpu_utils-3.3.14.data/scripts/amdgpu-monitor
ricks_amdgpu_utils-3.3.14.data/scripts/amdgpu-pac
ricks_amdgpu_utils-3.3.14.data/scripts/amdgpu-plot
ricks_amdgpu_utils-3.3.14.data/scripts/gpu-chk
ricks_amdgpu_utils-3.3.14.data/scripts/gpu-ls
ricks_amdgpu_utils-3.3.14.data/scripts/gpu-mon
ricks_amdgpu_utils-3.3.14.data/scripts/gpu-pac
ricks_amdgpu_utils-3.3.14.data/scripts/gpu-plot
ricks_amdgpu_utils-3.3.14.dist-info/LICENSE
ricks_amdgpu_utils-3.3.14.dist-info/METADATA
ricks_amdgpu_utils-3.3.14.dist-info/WHEEL
ricks_amdgpu_utils-3.3.14.dist-info/top_level.txt
ricks_amdgpu_utils-3.3.14.dist-info/RECORD
