Metadata-Version: 2.1
Name: ricks-amdgpu-utils
Version: 3.3.14
Summary: Ricks AMD GPU Utilities (Deprecated)
Home-page: https://github.com/Ricks-Lab/amdgpu-utils
Author: RueiKe
Author-email: rueikes.homelab@gmail.com
License: GPL-3
Platform: posix
Classifier: Development Status :: 6 - Mature
Classifier: Operating System :: POSIX
Classifier: Natural Language :: English
Classifier: Programming Language :: Python :: 3
Classifier: Topic :: System :: Monitoring
Requires-Python: >=3.6
Requires-Dist: cycler (>=0.10.0)
Requires-Dist: kiwisolver (>=1.1.0)
Requires-Dist: matplotlib (>=3.1.3)
Requires-Dist: numpy (>=1.18.1)
Requires-Dist: pandas (>=1.0.1)
Requires-Dist: pyparsing (>=2.4.6)
Requires-Dist: python-dateutil (>=2.8.1)
Requires-Dist: pytz (>=2019.3)
Requires-Dist: ruamel.yaml (==0.16.10)
Requires-Dist: ruamel.yaml.clib (==0.2.0)
Requires-Dist: six (>=1.11.0)
